Metadata-Version: 2.1
Name: say-me-something
Version: 0.1.1
Summary: A text to speak library with embedded cache system.
Home-page: https://github.com/onuratakan/say_me_something
Author: Onur Atakan ULUSOY
Author-email: atadogan06@gmail.com
License: MIT
Platform: UNKNOWN
Requires-Python: >=3
License-File: LICENSE
